{
	"id": "eWmyA6qW63iaaLk",
	"json": "{\"id\":\"eWmyA6qW63iaaLk\",\"url\":\"https://cococabanalife.com/pages/contact-us\",\"loadedUrl\":\"https://cococabanalife.com/pages/contact-us\",\"uniqueKey\":\"https://cococabanalife.com/pages/contact-us\",\"method\":\"GET\",\"noRetry\":false,\"retryCount\":0,\"errorMessages\":[],\"headers\":{},\"userData\":{\"__crawlee\":{\"state\":4}},\"handledAt\":\"2026-03-07T19:30:21.702Z\"}",
	"method": "GET",
	"orderNo": null,
	"retryCount": 0,
	"uniqueKey": "https://cococabanalife.com/pages/contact-us",
	"url": "https://cococabanalife.com/pages/contact-us"
}